aosp/__init__.py
aosp/aosp.py
aosp/env.py
aosp-0.1.0.dist-info/METADATA
aosp-0.1.0.dist-info/WHEEL
aosp-0.1.0.dist-info/top_level.txt
aosp-0.1.0.dist-info/RECORD
