Metadata-Version: 2.1
Name: aosp
Version: 0.1.0
Summary: Python wrapper for AOSP tasks
Author: Donghwi Kim
Author-email: dhkim09@kaist.ac.kr
Requires-Python: >=3.9
Requires-Dist: sh
Requires-Dist: yautil
Provides-Extra: test
Requires-Dist: sh ; extra == 'test'
Requires-Dist: yautil ; extra == 'test'
